{
  "public": {
    "title": "S.A.N.E.R - Situational Awareness for Novel Epidemic Response",
    "version": "v0.4.3",
    "fhirVersion": "R4",
    "contact": [
      {
        "telecom": [
          {
            "system": "email",
            "value": "abigail@symptomatic.healthcare"
          }
        ]
      }
    ],
    "smartOnFhir": [{
      "vendor": "SmartHealth IT",
      "client_id": "my-client-id",
      "scope": "launch launch/patient patient/read encounter/read procedure/read condition/read observation/read offline_access",
      "fhirServiceUrl": "https://launch.smarthealthit.org/v/r3/sim/",
      "redirect_uri": "./patient-quickchart",
      "iss": "https://launch.smarthealthit.org/v/r3/sim/eyJoIjoiMSIsImIiOiJmMDQ2MjkzNi1lYjRiLTRkYTEtYjQ1YS1mYmQ5NmViZjhjY2IiLCJlIjoic21hcnQtUHJhY3RpdGlvbmVyLTcxNjE0NTAyIn0/fhir"
    }],
    "theme": {
      "showVideoBackground": false,
      "defaultVideo": "/VideoBackgrounds/GrayWaves.mp4",
      "backgroundImagePath": "/backgrounds/medical/Gradient.jpg",
      "palette": {
        "primaryColor": "#FE5000",
        "primaryText": "rgba(255, 255, 255, 1) !important",
      
        "secondaryColor": "#FE5000",
        "secondaryText": "rgba(255, 255, 255, 1) !important",
      
        "cardColor": "#ffffff !important",
        "cardTextColor": "rgba(0, 0, 0, 1) !important",
      
        "errorColor": "rgb(128,20,60) !important",
        "errorText": "#ffffff !important",
      
        "appBarColor": "repeating-linear-gradient( 135deg, rgba(0, 0, 0, 0.45), rgba(0, 0, 0, 0.45) 5px, rgba(0, 0, 0, 0.5) 10px, rgba(0, 0, 0, 0.5) 10px ), url(http://s3-us-west-2.amazonaws.com/s.cdpn.io/3/old_map_@2X.png)",
        "appBarTextColor": "#ffffff !important",
      
        "paperColor": "#ffffff !important",
        "paperTextColor": "rgba(0, 0, 0, 1) !important",
      
        "backgroundCanvas": "#e6e6e6",
        "background": "linear-gradient(45deg, rgb(108, 183, 110) 30%, rgb(150, 202, 144) 90%)",

        "nivoTheme": "red_grey"
      },
      "grayscaleFilter": "100%"
    },
    "projectPage": {
      "carouselImages": [
        "https://raw.githubusercontent.com/symptomatic/node-on-fhir/development/docs/assets/ScreenShot-BulkDataQuery.png",
        "https://raw.githubusercontent.com/symptomatic/node-on-fhir/development/docs/assets/ScreenShot-ChicagoHospital-HeatMap.png",
        "https://raw.githubusercontent.com/symptomatic/node-on-fhir/development/docs/assets/Screenshot-PatientChart.png",
        "https://raw.githubusercontent.com/symptomatic/node-on-fhir/development/docs/assets/ScreenShot-ExportDataModule.png",
        "https://raw.githubusercontent.com/symptomatic/node-on-fhir/development/docs/assets/ScreenShot-Geomapping.png"
      ]
    },
    "loggingThreshold": "info",
    "capabilityStatement": {
      "resourceTypes": ["Condition", "Device", "Encounter", "Immunization", "Medication", "MedicationOrder", "MedicationRequest", "MedicationStatement", "Observation", "Procedure"]
    },
    "defaults": {
      "route": "/saner-hsa-map",
      "landingPage": "/saner-hsa-map",
      "homePage": "/saner-hsa-map",
      "landingModal": {
        "open": true,
        "title": "Welcome to S.A.N.E.R.",
        "component": "AboutDialog"
      },
      "dateFormat": "YYYY-MM-DD",
      "prominantHeader": true,
      "displayNavbars": true,
      "disableHeader": false,
      "disableFooter": false,
      "paginationLimit": 100,
      "subscriptionLimit": 1000,
      "sidebar": {
        "menuItems": {
          "HomePage": false,
          "FhirResources": false,
          "DynamicModules": true,
          "SidebarWorkflows": true,
          "Theme": false,
          "ConstructionZone": false
        },
        "hidden": [
          "/allergies",
          "/audit-events",
          "/body-mass-calculator",
          "/body-mass-index",
          "/bundles",
          "/careplans",
          "/communications",
          "/communication-responses",
          "/consents",
          "/contracts",          
          "/devices",
          "/diagnostic-reports",
          "/endpoints",
          "/example-route",
          "/explanation-of-benefits",
          "/goals",
          "/import-data",          
          "/imaging-studies",
          "/lists",
          "/medications",
          "/medication-orders",
          "/medication-statements",
          "/patients",
          "/practitioners",
          "/persons",
          "/questionnaires",
          "/questionnaire-responses",
          "/risk-assessments",
          "/subscriptions",
          "/tasks",
          "/valuesets",
          "/vitals-tracking"
        ],
        "hiddenWorkflow": [
          "/patient-quickchart",
          "/data-management",
          "/data-pipelines"
        ]
      }
    },
    "google": {
      "maps": {
        "apiKey": "AIzaSyCC3PHFkh1UvzuK9yykLa847jx2NeAU4LI",
        "geodataUrl": "",
        "mapCenter": "",
        "searchProximity": 50,
        "mapOptions": {
          "radius": 50,
          "opacity": 0.5,
          "dissipating": false,
          "maxIntensity": 50,
          "gradient": [
            "rgba(255, 255, 255, 0)",
            "rgba(251, 251, 213, 1)",
            "rgba(249, 234, 189, 1)",
            "rgba(247, 217, 165, 1)",
            "rgba(243, 184, 118, 1)",
            "rgba(242, 168, 94, 1)",
            "rgba(240, 151, 71, 1)",
            "rgba(238, 135, 47, 1)",
            "rgba(236, 118, 23, 1)",
            "rgba(210, 80, 0, 1)"
          ]
        }
      }
    },
    "interfaces": {
      "default": {
        "status": "active",
        "channel": {
          "endpoint": "https://covid19-under-fhir.smilecdr.com/baseR4"
        },
        "auth": {
          "username": "foo",
          "password": "bar"
        }
      }
    },
    "meshNetwork": {
      "upstreamSync": "http://meteor-on-fhir.meteorapp.com/fhir-3.0.0", 
      "autosync": false
    }
  },
  "private": {
    "storeHospitalIndexInMongo": true,
    "fhir": {
      "disableOauth": true,
      "fhirPath": "baseR4",
      "rest": {
        "Communication": {
          "interactions": ["read", "create"]
        },
        "CommunicationsResponse": true,
        "Location": true,
        "Measure": true,
        "MeasureReport": {
          "interactions": ["read", "create", "update", "delete"]
        },
        "Organization": true,
        "Questionnaire": true,
        "QuestionnaireResponse": true
      }
    }
  },
  "galaxy.meteor.com": {
    "env": {
      "MONGO_URL": "mongodb+srv://healthadmin:X0R8R1H97vU0HhcM@covid19-qch1n.mongodb.net/covid19?retryWrites=true&w=majority",
      "MONGO_OPLOG_URL": "mongodb+srv://oplog:nZyUkEwrf54QKDl5@covid19-qch1n.mongodb.net/local?retryWrites=true&w=majority&authSource=admin&ssl=true&replicaSet=Covid19-shard-0",
      "NODE_ENV": "test",
      "ROOT_URL": "https://gravity.meteorapp.com",
      "DEBUG": 1,
      "TRACE": 0
    }
  }
}
