{
  "resourceType" : "ValueSet",
  "id" : "BedTypeOfCare",
  "text" : {
    "status" : "generated",
    "div" : "<div xmlns=\"http://www.w3.org/1999/xhtml\"><h2>Bed Type of Care</h2><div><p>This Value Set describes the types of care services that a bed can support.</p>\n</div><p>This value set includes codes based on the following rules:</p><ul><li>Include these codes as defined in <a href=\"http://hl7.org/fhir/R4/v3/RoleCode/cs.html\"><code>http://terminology.hl7.org/CodeSystem/v3-RoleCode</code></a><table class=\"none\"><tr><td style=\"white-space:nowrap\"><b>Code</b></td><td><b>Display</b></td></tr><tr><td><a href=\"http://hl7.org/fhir/R4/v3/RoleCode/cs.html#v3-RoleCode-HOSP\">HOSP</a></td><td>Hospital</td><td>An acute care institution that provides medical, surgical, or psychiatric care and treatment for the sick or the injured.</td></tr><tr><td><a href=\"http://hl7.org/fhir/R4/v3/RoleCode/cs.html#v3-RoleCode-ICU\">ICU</a></td><td>Intensive care unit</td><td>Intensive care unit</td></tr><tr><td><a href=\"http://hl7.org/fhir/R4/v3/RoleCode/cs.html#v3-RoleCode-ER\">ER</a></td><td>Emergency room</td><td>The section of a health care facility for providing rapid treatment to victims of sudden illness or trauma.</td></tr></table></li><li>Include these codes as defined in <a href=\"CodeSystem-BedType.html\"><code>http://hl7.org/fhir/us/saner/CodeSystem/BedType</code></a><table class=\"none\"><tr><td style=\"white-space:nowrap\"><b>Code</b></td><td><b>Display</b></td></tr><tr><td><a href=\"CodeSystem-BedType.html#BedType-OR\">OR</a></td><td>Operating Room</td><td>Operating Rooms used for surgical procedures. When a room is used for both surgical andnon-surgical procedures, it should be classified as an operating room.</td></tr><tr><td><a href=\"CodeSystem-BedType.html#BedType-NURSERY\">NURSERY</a></td><td>Nursery</td><td>Room used for Nursery</td></tr><tr><td><a href=\"CodeSystem-BedType.html#BedType-BURNU\">BURNU</a></td><td>Burn Unit</td><td>Beds in a Burn Unit</td></tr></table></li></ul></div>"
  },
  "url" : "http://hl7.org/fhir/us/saner/ValueSet/BedTypeOfCare",
  "version" : "0.1.0",
  "name" : "BedTypeOfCare",
  "title" : "Bed Type of Care",
  "status" : "active",
  "date" : "2020-05-15T14:48:47+00:00",
  "publisher" : "HL7 International",
  "contact" : [
    {
      "name" : "HL7 Patient Administration Workgroup",
      "telecom" : [
        {
          "system" : "url",
          "value" : "http://hl7.org/Special/committees/pafm/index.cfm"
        }
      ]
    },
    {
      "name" : "Audacious Inquiry",
      "telecom" : [
        {
          "system" : "url",
          "value" : "http://ainq.com"
        }
      ]
    },
    {
      "name" : "Keith W. Boone",
      "telecom" : [
        {
          "system" : "email",
          "value" : "mailto:kboone@ainq.com"
        }
      ]
    }
  ],
  "description" : "This Value Set describes the types of care services that a bed can support.",
  "compose" : {
    "include" : [
      {
        "system" : "http://terminology.hl7.org/CodeSystem/v3-RoleCode",
        "concept" : [
          {
            "code" : "HOSP"
          },
          {
            "code" : "ICU"
          },
          {
            "code" : "ER"
          }
        ]
      },
      {
        "system" : "http://hl7.org/fhir/us/saner/CodeSystem/BedType",
        "concept" : [
          {
            "code" : "OR"
          },
          {
            "code" : "NURSERY"
          },
          {
            "code" : "BURNU"
          }
        ]
      }
    ]
  }
}